Metadata-Version: 2.1
Name: sqlite-utils-move-tables
Version: 0.1
Summary: Command for sqlite-utils to move tables from one database to another
Author: Simon Willison
License: Apache-2.0
Project-URL: Homepage, https://github.com/simonw/sqlite-utils-move-tables
Project-URL: Changelog, https://github.com/simonw/sqlite-utils-move-tables/releases
Project-URL: Issues, https://github.com/simonw/sqlite-utils-move-tables/issues
Project-URL: CI, https://github.com/simonw/sqlite-utils-move-tables/actions
Classifier: License :: OSI Approved :: Apache Software License
License-File: LICENSE
Requires-Dist: sqlite-utils
Provides-Extra: test
Requires-Dist: pytest ; extra == 'test'
